counter.vhd
--Contador de un segundo
library IEEE;
use IEEE.std_logic_1164.all;
use IEEE.numeric_std.all;

entity counter is
    --Para simulaciones se setea a N := 6 y a M := 49 y es un contador un microsegundo)
    generic(N: natural := 26; M: integer := 49999999);

    port (ena: in std_logic;
          clk: in std_logic;  
          rst: in std_logic;
          qo: out std_logic_vector(N-1 downto 0);
          max: out std_logic := '0'
          );
end counter;

architecture counter_beh of counter is
    signal aux: unsigned(N-1 downto 0);
begin
    process(clk, rst)
    begin
        if rst = '1' then
            aux <= (others => '0');
            max <= '0';
        end if;
        if rising_edge(clk) then
            --Si está habilitado
            if ena = '1' then
                --Sumar
                aux <= aux + 1;
                --Si se pasó poner en cero 
                if aux = to_unsigned(M, N) then
                    aux <= (others =>'0');
                    max <= '1';
                else
                    max <= '0';
                end if;
            end if;
            qo <= std_logic_vector(aux); 
        end if;
    end process;
end counter_beh;

counter_semaforos.vhd
library IEEE;
use IEEE.std_logic_1164.all;
use IEEE.numeric_std.all;

library work;
use work.semaforos_states.all;

entity counter_semf is
    generic (
        N_SEMF : natural := 5;
        N_SEG_COUNTER : natural := 26);
    port (
        ena_semf_counter : in std_logic;
        clk_semf_counter : in std_logic;
        rst_semf_counter : in std_logic;
        state : in semf_states;
        qo_semf_counter : out std_logic_vector(N_SEMF - 1 downto 0);
        max_semf_counter : out std_logic
    );
end counter_semf;

architecture counter_semf_beh of counter_semf is
    signal aux : unsigned(N_SEMF - 1 downto 0);
    signal qo_seg : std_logic_vector(N_SEG_COUNTER - 1 downto 0);
    signal add : std_logic;
    constant T1: integer := 30;
    constant T2: integer := 3;

begin
    COUNTER_INST : entity work.counter(counter_beh)
        generic map(N => N_SEG_COUNTER)
        port map(
            ena => ena_semf_counter,
            clk => clk_semf_counter,
            rst => rst_semf_counter,
            qo => qo_seg,
            max => add
        );

    P_CLK : process (clk_semf_counter, rst_semf_counter)
    begin
        --Si reset está activado
        if rst_semf_counter = '1' then
            aux <= (others => '0');
            max <= '0';
        end if;
        if rising_edge(clk_semf_counter) then
            --Si está habilitado
            if ena_semf_counter = '1' then
                if state = E0 or state = E3 then
                    if aux = to_unsigned(T1, N_SEMF) then
                        aux <= (others => '0');
                        max_semf_counter <= '1';
                    else
                        if add = '1' then
                            aux <= aux + 1;
                        end if;
                        max_semf_counter <= '0';
                    end if;
                else
                    if aux = to_unsigned(T2, N_SEMF) then
                        aux <= (others => '0');
                        max_semf_counter <= '1';
                    else
                        if add = '1' then
                            aux <= aux + 1;
                        end if;
                        max_semf_counter <= '0';
                    end if;
                end if;
            end if;
            qo_semf_counter <= std_logic_vector(aux);
        end if;
    end process P_CLK;

end counter_semf_beh;

semaforos.vhd
library IEEE;
use IEEE.std_logic_1164.all;
use IEEE.numeric_std.all;

library work;
use work.semaforos_states.all;

entity semaforos is
    port (
        clk_semf : in std_logic;
        rst_semf : in std_logic;
        ena_semf : in std_logic;
        green1 : out std_logic;
        yellow1 : out std_logic;
        red1 : out std_logic;
        green2 : out std_logic;
        yellow2 : out std_logic;
        red2 : out std_logic);
end semaforos;

architecture semaforos_beh of semaforos is
    signal current_state : semf_states;
    signal event : std_logic;
begin
    COUNTER_SEMF_INSTANCE : entity work.counter_semf(counter_semf_beh)
        port map(
            ena_semf_counter => ena_semf,
            rst_semf_counter => rst_semf,
            state => current_state,
            max_semf_counter => event,
            clk_semf_counter => clk_semf);

    P_SEMF_FSM : process (clk_semf, rst_semf)
    begin
        --Si reset activado volver al estado inicial
        if rst_semf = '1' then
            current_state <= E0;
        end if;

        if rising_edge(clk_semf) then
            if ena_semf = '1' then
                if event = '1' then
                    C_SEMF : case current_state is
                            --E0 => E1
                        when E0 =>
                            current_state <= E1;

                            --E1 => E2
                        when E1 =>
                            current_state <= E2;

                            --E2 => E3
                        when E2 =>
                            current_state <= E3;

                            --E3 => E4
                        when E3 =>
                            current_state <= E4;

                            --E4 => E5
                        when  E4 =>
                            current_state <= E5;

                            --E5 => E0
                        when E5 =>
                            current_state <= E0;
                        when others =>
                    end case C_SEMF;
                end if;
            end if;
        end if;
    end process P_SEMF_FSM;

    --Asignación de luces dependiendo del estado actual
    --Semáforo 1
    red1 <= '1' when (current_state = E0 or current_state = E1 or current_state = E5) else '0';
    yellow1 <= '1' when (current_state = E2 or current_state = E4) else '0';
    green1 <= '1' when current_state = E3 else '0';
    --Semáforo 2
    red2 <= '1' when (current_state = E2 or current_state = E3 or current_state = E4) else '0';
    green2 <= '1' when current_state = E0 else '0';
    yellow2 <= '1' when (current_state = E1 or current_state = E5) else '0';


end semaforos_beh;

semaforos_tb.vhd
library IEEE;
use IEEE.std_logic_1164.all;
use IEEE.numeric_std.all;

entity semaforos_tb is
end semaforos_tb;

architecture semaforos_tb_beh of semaforos_tb is
    signal clk_semf_tb : std_logic := '0';
    signal rst_semf_tb : std_logic := '1';
    signal ena_semf_tb : std_logic := '0';
    signal green1_tb : std_logic;
    signal yellow1_tb : std_logic;
    signal red1_tb : std_logic;
    signal green2_tb : std_logic;
    signal yellow2_tb : std_logic;
    signal red2_tb : std_logic;
begin
    SEMAFOROS_INST: entity work.semaforos(semaforos_beh)
    port map(
        clk_semf => clk_semf_tb,
        rst_semf => rst_semf_tb,
        ena_semf => ena_semf_tb,
        green1 => green1_tb,
        yellow1 => yellow1_tb,
        red1 => red1_tb,
        green2 => green2_tb,
        yellow2 => yellow2_tb,
        red2 => red2_tb);

        rst_semf_tb <= '0' after 1 us;
        ena_semf_tb <= '1' after 1 us;
        clk_semf_tb <= not clk_semf_tb after 10 ns; 
end semaforos_tb_beh;

semaforos_tb.vcd
$date
  Fri Sep 29 15:19:50 2023
$end
$version
  GHDL v0
$end
$timescale
  1 fs
$end
$scope module standard $end
$upscope $end
$scope module std_logic_1164 $end
$upscope $end
$scope module numeric_std $end
$upscope $end
$scope module semaforos_states $end
$upscope $end
$scope module semaforos_tb $end
$var reg 1 ! clk_semf_tb $end
$var reg 1 " rst_semf_tb $end
$var reg 1 # ena_semf_tb $end
$var reg 1 $ green1_tb $end
$var reg 1 % yellow1_tb $end
$var reg 1 & red1_tb $end
$var reg 1 ' green2_tb $end
$var reg 1 ( yellow2_tb $end
$var reg 1 ) red2_tb $end
$scope module semaforos_inst $end
$var reg 1 * clk_semf $end
$var reg 1 + rst_semf $end
$var reg 1 , ena_semf $end
$var reg 1 - green1 $end
$var reg 1 . yellow1 $end
$var reg 1 / red1 $end
$var reg 1 0 green2 $end
$var reg 1 1 yellow2 $end
$var reg 1 2 red2 $end
$comment current_state is not handled $end
$var reg 1 3 event $end
$scope module counter_semf_instance $end
$var reg 1 4 ena_semf_counter $end
$var reg 1 5 clk_semf_counter $end
$var reg 1 6 rst_semf_counter $end
$comment state is not handled $end
$var reg 5 7 qo_semf_counter[4:0] $end
$var reg 1 8 max_semf_counter $end
$var reg 5 9 aux[4:0] $end
$var reg 26 : qo_seg[25:0] $end
$var reg 1 ; add $end
$scope module counter_inst $end
$var reg 1 < ena $end
$var reg 1 = clk $end
$var reg 1 > rst $end
$var reg 26 ? qo[25:0] $end
$var reg 1 @ max $end
$var reg 26 A aux[25:0] $end
$upscope $end
$upscope $end
$upscope $end
$upscope $end
$enddefinitions $end
#0
0!
1"
0#
0$
0%
1&
1'
0(
0)
0*
1+
0,
0-
0.
1/
10
01
02
03
04
05
16
bUUUUU 7
08
b00000 9
bUUUUUUUUUUUUUUUUUUUUUUUUUU :
0;
0<
0=
1>
bUUUUUUUUUUUUUUUUUUUUUUUUUU ?
0@
b00000000000000000000000000 A
#10000000
1!
1*
15
b00000 7
b00000000000000000000000000 :
1=
b00000000000000000000000000 ?
#20000000
0!
0*
05
0=
#30000000
1!
1*
15
1=
#40000000
0!
0*
05
0=
#50000000
1!
1*
15
1=
#60000000
0!
0*
05
0=
#70000000
1!
1*
15
1=
#80000000
0!
0*
05
0=
#90000000
1!
1*
15
1=
#100000000
0!
0*
05
0=
#110000000
1!
1*
15
1=
#120000000
0!
0*
05
0=
#130000000
1!
1*
15
1=
#140000000
0!
0*
05
0=
#150000000
1!
1*
15
1=
#160000000
0!
0*
05
0=
#170000000
1!
1*
15
1=
#180000000
0!
0*
05
0=
#190000000
1!
1*
15
1=
#200000000
0!
0*
05
0=
#210000000
1!
1*
15
1=
#220000000
0!
0*
05
0=
#230000000
1!
1*
15
1=
#240000000
0!
0*
05
0=
#250000000
1!
1*
15
1=
#260000000
0!
0*
05
0=
#270000000
1!
1*
15
1=
#280000000
0!
0*
05
0=
#290000000
1!
1*
15
1=
#300000000
0!
0*
05
0=
#310000000
1!
1*
15
1=
#320000000
0!
0*
05
0=
#330000000
1!
1*
15
1=
#340000000
0!
0*
05
0=
#350000000
1!
1*
15
1=
#360000000
0!
0*
05
0=
#370000000
1!
1*
15
1=
#380000000
0!
0*
05
0=
#390000000
1!
1*
15
1=
#400000000
0!
0*
05
0=
#410000000
1!
1*
15
1=
#420000000
0!
0*
05
0=
#430000000
1!
1*
15
1=
#440000000
0!
0*
05
0=
#450000000
1!
1*
15
1=
#460000000
0!
0*
05
0=
#470000000
1!
1*
15
1=
#480000000
0!
0*
05
0=
#490000000
1!
1*
15
1=
#500000000
0!
0*
05
0=
#510000000
1!
1*
15
1=
#520000000
0!
0*
05
0=
#530000000
1!
1*
15
1=
#540000000
0!
0*
05
0=
#550000000
1!
1*
15
1=
#560000000
0!
0*
05
0=
#570000000
1!
1*
15
1=
#580000000
0!
0*
05
0=
#590000000
1!
1*
15
1=
#600000000
0!
0*
05
0=
#610000000
1!
1*
15
1=
#620000000
0!
0*
05
0=
#630000000
1!
1*
15
1=
#640000000
0!
0*
05
0=
#650000000
1!
1*
15
1=
#660000000
0!
0*
05
0=
#670000000
1!
1*
15
1=
#680000000
0!
0*
05
0=
#690000000
1!
1*
15
1=
#700000000
0!
0*
05
0=
#710000000
1!
1*
15
1=
#720000000
0!
0*
05
0=
#730000000
1!
1*
15
1=
#740000000
0!
0*
05
0=
#750000000
1!
1*
15
1=
#760000000
0!
0*
05
0=
#770000000
1!
1*
15
1=
#780000000
0!
0*
05
0=
#790000000
1!
1*
15
1=
#800000000
0!
0*
05
0=
#810000000
1!
1*
15
1=
#820000000
0!
0*
05
0=
#830000000
1!
1*
15
1=
#840000000
0!
0*
05
0=
#850000000
1!
1*
15
1=
#860000000
0!
0*
05
0=
#870000000
1!
1*
15
1=
#880000000
0!
0*
05
0=
#890000000
1!
1*
15
1=
#900000000
0!
0*
05
0=
#910000000
1!
1*
15
1=
#920000000
0!
0*
05
0=
#930000000
1!
1*
15
1=
#940000000
0!
0*
05
0=
#950000000
1!
1*
15
1=
#960000000
0!
0*
05
0=
#970000000
1!
1*
15
1=
#980000000
0!
0*
05
0=
#990000000
1!
1*
15
1=
#1000000000
0!
0"
1#
0*
0+
1,
14
05
06
1<
0=
0>
#1010000000
1!
1*
15
1=
b00000000000000000000000001 A
#1020000000
0!
0*
05
0=
#1030000000
1!
1*
15
b00000000000000000000000001 :
1=
b00000000000000000000000001 ?
b00000000000000000000000010 A
#1040000000
0!
0*
05
0=
#1050000000
1!
1*
15
b00000000000000000000000010 :
1=
b00000000000000000000000010 ?
b00000000000000000000000011 A
#1060000000
0!
0*
05
0=
#1070000000
1!
1*
15
b00000000000000000000000011 :
1=
b00000000000000000000000011 ?
b00000000000000000000000100 A
#1080000000
0!
0*
05
0=
#1090000000
1!
1*
15
b00000000000000000000000100 :
1=
b00000000000000000000000100 ?
b00000000000000000000000101 A
#1100000000
0!
0*
05
0=
#1110000000
1!
1*
15
b00000000000000000000000101 :
1=
b00000000000000000000000101 ?
b00000000000000000000000110 A
#1120000000
0!
0*
05
0=
#1130000000
1!
1*
15
b00000000000000000000000110 :
1=
b00000000000000000000000110 ?
b00000000000000000000000111 A
#1140000000
0!
0*
05
0=
#1150000000
1!
1*
15
b00000000000000000000000111 :
1=
b00000000000000000000000111 ?
b00000000000000000000001000 A
#1160000000
0!
0*
05
0=
#1170000000
1!
1*
15
b00000000000000000000001000 :
1=
b00000000000000000000001000 ?
b00000000000000000000001001 A
#1180000000
0!
0*
05
0=
#1190000000
1!
1*
15
b00000000000000000000001001 :
1=
b00000000000000000000001001 ?
b00000000000000000000001010 A
#1200000000
0!
0*
05
0=
#1210000000
1!
1*
15
b00000000000000000000001010 :
1=
b00000000000000000000001010 ?
b00000000000000000000001011 A
#1220000000
0!
0*
05
0=
#1230000000
1!
1*
15
b00000000000000000000001011 :
1=
b00000000000000000000001011 ?
b00000000000000000000001100 A
#1240000000
0!
0*
05
0=
#1250000000
1!
1*
15
b00000000000000000000001100 :
1=
b00000000000000000000001100 ?
b00000000000000000000001101 A
#1260000000
0!
0*
05
0=
#1270000000
1!
1*
15
b00000000000000000000001101 :
1=
b00000000000000000000001101 ?
b00000000000000000000001110 A
#1280000000
0!
0*
05
0=
#1290000000
1!
1*
15
b00000000000000000000001110 :
1=
b00000000000000000000001110 ?
b00000000000000000000001111 A
#1300000000
0!
0*
05
0=
#1310000000
1!
1*
15
b00000000000000000000001111 :
1=
b00000000000000000000001111 ?
b00000000000000000000010000 A
#1320000000
0!
0*
05
0=
#1330000000
1!
1*
15
b00000000000000000000010000 :
1=
b00000000000000000000010000 ?
b00000000000000000000010001 A
#1340000000
0!
0*
05
0=
#1350000000
1!
1*
15
b00000000000000000000010001 :
1=
b00000000000000000000010001 ?
b00000000000000000000010010 A
#1360000000
0!
0*
05
0=
#1370000000
1!
1*
15
b00000000000000000000010010 :
1=
b00000000000000000000010010 ?
b00000000000000000000010011 A
#1380000000
0!
0*
05
0=
#1390000000
1!
1*
15
b00000000000000000000010011 :
1=
b00000000000000000000010011 ?
b00000000000000000000010100 A
#1400000000
0!
0*
05
0=
#1410000000
1!
1*
15
b00000000000000000000010100 :
1=
b00000000000000000000010100 ?
b00000000000000000000010101 A
#1420000000
0!
0*
05
0=
#1430000000
1!
1*
15
b00000000000000000000010101 :
1=
b00000000000000000000010101 ?
b00000000000000000000010110 A
#1440000000
0!
0*
05
0=
#1450000000
1!
1*
15
b00000000000000000000010110 :
1=
b00000000000000000000010110 ?
b00000000000000000000010111 A
#1460000000
0!
0*
05
0=
#1470000000
1!
1*
15
b00000000000000000000010111 :
1=
b00000000000000000000010111 ?
b00000000000000000000011000 A
#1480000000
0!
0*
05
0=
#1490000000
1!
1*
15
b00000000000000000000011000 :
1=
b00000000000000000000011000 ?
b00000000000000000000011001 A
#1500000000
0!
0*
05
0=
#1510000000
1!
1*
15
b00000000000000000000011001 :
1=
b00000000000000000000011001 ?
b00000000000000000000011010 A
#1520000000
0!
0*
05
0=
#1530000000
1!
1*
15
b00000000000000000000011010 :
1=
b00000000000000000000011010 ?
b00000000000000000000011011 A
#1540000000
0!
0*
05
0=
#1550000000
1!
1*
15
b00000000000000000000011011 :
1=
b00000000000000000000011011 ?
b00000000000000000000011100 A
#1560000000
0!
0*
05
0=
#1570000000
1!
1*
15
b00000000000000000000011100 :
1=
b00000000000000000000011100 ?
b00000000000000000000011101 A
#1580000000
0!
0*
05
0=
#1590000000
1!
1*
15
b00000000000000000000011101 :
1=
b00000000000000000000011101 ?
b00000000000000000000011110 A
#1600000000
0!
0*
05
0=
#1610000000
1!
1*
15
b00000000000000000000011110 :
1=
b00000000000000000000011110 ?
b00000000000000000000011111 A
#1620000000
0!
0*
05
0=
#1630000000
1!
1*
15
b00000000000000000000011111 :
1=
b00000000000000000000011111 ?
b00000000000000000000100000 A
#1640000000
0!
0*
05
0=
#1650000000
1!
1*
15
b00000000000000000000100000 :
1=
b00000000000000000000100000 ?
b00000000000000000000100001 A
#1660000000
0!
0*
05
0=
#1670000000
1!
1*
15
b00000000000000000000100001 :
1=
b00000000000000000000100001 ?
b00000000000000000000100010 A
#1680000000
0!
0*
05
0=
#1690000000
1!
1*
15
b00000000000000000000100010 :
1=
b00000000000000000000100010 ?
b00000000000000000000100011 A
#1700000000
0!
0*
05
0=
#1710000000
1!
1*
15
b00000000000000000000100011 :
1=
b00000000000000000000100011 ?
b00000000000000000000100100 A
#1720000000
0!
0*
05
0=
#1730000000
1!
1*
15
b00000000000000000000100100 :
1=
b00000000000000000000100100 ?
b00000000000000000000100101 A
#1740000000
0!
0*
05
0=
#1750000000
1!
1*
15
b00000000000000000000100101 :
1=
b00000000000000000000100101 ?
b00000000000000000000100110 A
#1760000000
0!
0*
05
0=
#1770000000
1!
1*
15
b00000000000000000000100110 :
1=
b00000000000000000000100110 ?
b00000000000000000000100111 A
#1780000000
0!
0*
05
0=
#1790000000
1!
1*
15
b00000000000000000000100111 :
1=
b00000000000000000000100111 ?
b00000000000000000000101000 A
#1800000000
0!
0*
05
0=
#1810000000
1!
1*
15
b00000000000000000000101000 :
1=
b00000000000000000000101000 ?
b00000000000000000000101001 A
#1820000000
0!
0*
05
0=
#1830000000
1!
1*
15
b00000000000000000000101001 :
1=
b00000000000000000000101001 ?
b00000000000000000000101010 A
#1840000000
0!
0*
05
0=
#1850000000
1!
1*
15
b00000000000000000000101010 :
1=
b00000000000000000000101010 ?
b00000000000000000000101011 A
#1860000000
0!
0*
05
0=
#1870000000
1!
1*
15
b00000000000000000000101011 :
1=
b00000000000000000000101011 ?
b00000000000000000000101100 A
#1880000000
0!
0*
05
0=
#1890000000
1!
1*
15
b00000000000000000000101100 :
1=
b00000000000000000000101100 ?
b00000000000000000000101101 A
#1900000000
0!
0*
05
0=
#1910000000
1!
1*
15
b00000000000000000000101101 :
1=
b00000000000000000000101101 ?
b00000000000000000000101110 A
#1920000000
0!
0*
05
0=
#1930000000
1!
1*
15
b00000000000000000000101110 :
1=
b00000000000000000000101110 ?
b00000000000000000000101111 A
#1940000000
0!
0*
05
0=
#1950000000
1!
1*
15
b00000000000000000000101111 :
1=
b00000000000000000000101111 ?
b00000000000000000000110000 A
#1960000000
0!
0*
05
0=
#1970000000
1!
1*
15
b00000000000000000000110000 :
1=
b00000000000000000000110000 ?
b00000000000000000000110001 A
#1980000000
0!
0*
05
0=
#1990000000
1!
1*
15
b00000000000000000000110001 :
1=
b00000000000000000000110001 ?
b00000000000000000000110010 A
#2000000000
0!
0*
05
0=
#2010000000
1!
1*
15
b00000000000000000000110010 :
1=
b00000000000000000000110010 ?
b00000000000000000000110011 A
#2020000000
0!
0*
05
0=
#2030000000
1!
1*
15
b00000000000000000000110011 :
1=
b00000000000000000000110011 ?
b00000000000000000000110100 A
#2040000000
0!
0*
05
0=
#2050000000
1!
1*
15
b00000000000000000000110100 :
1=
b00000000000000000000110100 ?
b00000000000000000000110101 A
#2060000000
0!
0*
05
0=
#2070000000
1!
1*
15
b00000000000000000000110101 :
1=
b00000000000000000000110101 ?
b00000000000000000000110110 A
#2080000000
0!
0*
05
0=
#2090000000
1!
1*
15
b00000000000000000000110110 :
1=
b00000000000000000000110110 ?
b00000000000000000000110111 A
#2100000000
0!
0*
05
0=
#2110000000
1!
1*
15
b00000000000000000000110111 :
1=
b00000000000000000000110111 ?
b00000000000000000000111000 A
#2120000000
0!
0*
05
0=
#2130000000
1!
1*
15
b00000000000000000000111000 :
1=
b00000000000000000000111000 ?
b00000000000000000000111001 A
#2140000000
0!
0*
05
0=
#2150000000
1!
1*
15
b00000000000000000000111001 :
1=
b00000000000000000000111001 ?
b00000000000000000000111010 A
#2160000000
0!
0*
05
0=
#2170000000
1!
1*
15
b00000000000000000000111010 :
1=
b00000000000000000000111010 ?
b00000000000000000000111011 A
#2180000000
0!
0*
05
0=
#2190000000
1!
1*
15
b00000000000000000000111011 :
1=
b00000000000000000000111011 ?
b00000000000000000000111100 A
#2200000000
0!
0*
05
0=
#2210000000
1!
1*
15
b00000000000000000000111100 :
1=
b00000000000000000000111100 ?
b00000000000000000000111101 A
#2220000000
0!
0*
05
0=
#2230000000
1!
1*
15
b00000000000000000000111101 :
1=
b00000000000000000000111101 ?
b00000000000000000000111110 A
#2240000000
0!
0*
05
0=
#2250000000
1!
1*
15
b00000000000000000000111110 :
1=
b00000000000000000000111110 ?
b00000000000000000000111111 A
#2260000000
0!
0*
05
0=
#2270000000
1!
1*
15
b00000000000000000000111111 :
1=
b00000000000000000000111111 ?
b00000000000000000001000000 A
#2280000000
0!
0*
05
0=
#2290000000
1!
1*
15
b00000000000000000001000000 :
1=
b00000000000000000001000000 ?
b00000000000000000001000001 A
#2300000000
0!
0*
05
0=
#2310000000
1!
1*
15
b00000000000000000001000001 :
1=
b00000000000000000001000001 ?
b00000000000000000001000010 A
#2320000000
0!
0*
05
0=
#2330000000
1!
1*
15
b00000000000000000001000010 :
1=
b00000000000000000001000010 ?
b00000000000000000001000011 A
#2340000000
0!
0*
05
0=
#2350000000
1!
1*
15
b00000000000000000001000011 :
1=
b00000000000000000001000011 ?
b00000000000000000001000100 A
#2360000000
0!
0*
05
0=
#2370000000
1!
1*
15
b00000000000000000001000100 :
1=
b00000000000000000001000100 ?
b00000000000000000001000101 A
#2380000000
0!
0*
05
0=
#2390000000
1!
1*
15
b00000000000000000001000101 :
1=
b00000000000000000001000101 ?
b00000000000000000001000110 A
#2400000000
0!
0*
05
0=
#2410000000
1!
1*
15
b00000000000000000001000110 :
1=
b00000000000000000001000110 ?
b00000000000000000001000111 A
#2420000000
0!
0*
05
0=
#2430000000
1!
1*
15
b00000000000000000001000111 :
1=
b00000000000000000001000111 ?
b00000000000000000001001000 A
#2440000000
0!
0*
05
0=
#2450000000
1!
1*
15
b00000000000000000001001000 :
1=
b00000000000000000001001000 ?
b00000000000000000001001001 A
#2460000000
0!
0*
05
0=
#2470000000
1!
1*
15
b00000000000000000001001001 :
1=
b00000000000000000001001001 ?
b00000000000000000001001010 A
#2480000000
0!
0*
05
0=
#2490000000
1!
1*
15
b00000000000000000001001010 :
1=
b00000000000000000001001010 ?
b00000000000000000001001011 A
#2500000000
0!
0*
05
0=
#2510000000
1!
1*
15
b00000000000000000001001011 :
1=
b00000000000000000001001011 ?
b00000000000000000001001100 A
#2520000000
0!
0*
05
0=
#2530000000
1!
1*
15
b00000000000000000001001100 :
1=
b00000000000000000001001100 ?
b00000000000000000001001101 A
#2540000000
0!
0*
05
0=
#2550000000
1!
1*
15
b00000000000000000001001101 :
1=
b00000000000000000001001101 ?
b00000000000000000001001110 A
#2560000000
0!
0*
05
0=
#2570000000
1!
1*
15
b00000000000000000001001110 :
1=
b00000000000000000001001110 ?
b00000000000000000001001111 A
#2580000000
0!
0*
05
0=
#2590000000
1!
1*
15
b00000000000000000001001111 :
1=
b00000000000000000001001111 ?
b00000000000000000001010000 A
#2600000000
0!
0*
05
0=
#2610000000
1!
1*
15
b00000000000000000001010000 :
1=
b00000000000000000001010000 ?
b00000000000000000001010001 A
#2620000000
0!
0*
05
0=
#2630000000
1!
1*
15
b00000000000000000001010001 :
1=
b00000000000000000001010001 ?
b00000000000000000001010010 A
#2640000000
0!
0*
05
0=
#2650000000
1!
1*
15
b00000000000000000001010010 :
1=
b00000000000000000001010010 ?
b00000000000000000001010011 A
#2660000000
0!
0*
05
0=
#2670000000
1!
1*
15
b00000000000000000001010011 :
1=
b00000000000000000001010011 ?
b00000000000000000001010100 A
#2680000000
0!
0*
05
0=
#2690000000
1!
1*
15
b00000000000000000001010100 :
1=
b00000000000000000001010100 ?
b00000000000000000001010101 A
#2700000000
0!
0*
05
0=
#2710000000
1!
1*
15
b00000000000000000001010101 :
1=
b00000000000000000001010101 ?
b00000000000000000001010110 A
#2720000000
0!
0*
05
0=
#2730000000
1!
1*
15
b00000000000000000001010110 :
1=
b00000000000000000001010110 ?
b00000000000000000001010111 A
#2740000000
0!
0*
05
0=
#2750000000
1!
1*
15
b00000000000000000001010111 :
1=
b00000000000000000001010111 ?
b00000000000000000001011000 A
#2760000000
0!
0*
05
0=
#2770000000
1!
1*
15
b00000000000000000001011000 :
1=
b00000000000000000001011000 ?
b00000000000000000001011001 A
#2780000000
0!
0*
05
0=
#2790000000
1!
1*
15
b00000000000000000001011001 :
1=
b00000000000000000001011001 ?
b00000000000000000001011010 A
#2800000000
0!
0*
05
0=
#2810000000
1!
1*
15
b00000000000000000001011010 :
1=
b00000000000000000001011010 ?
b00000000000000000001011011 A
#2820000000
0!
0*
05
0=
#2830000000
1!
1*
15
b00000000000000000001011011 :
1=
b00000000000000000001011011 ?
b00000000000000000001011100 A
#2840000000
0!
0*
05
0=
#2850000000
1!
1*
15
b00000000000000000001011100 :
1=
b00000000000000000001011100 ?
b00000000000000000001011101 A
#2860000000
0!
0*
05
0=
#2870000000
1!
1*
15
b00000000000000000001011101 :
1=
b00000000000000000001011101 ?
b00000000000000000001011110 A
#2880000000
0!
0*
05
0=
#2890000000
1!
1*
15
b00000000000000000001011110 :
1=
b00000000000000000001011110 ?
b00000000000000000001011111 A
#2900000000
0!
0*
05
0=
#2910000000
1!
1*
15
b00000000000000000001011111 :
1=
b00000000000000000001011111 ?
b00000000000000000001100000 A
#2920000000
0!
0*
05
0=
#2930000000
1!
1*
15
b00000000000000000001100000 :
1=
b00000000000000000001100000 ?
b00000000000000000001100001 A
#2940000000
0!
0*
05
0=
#2950000000
1!
1*
15
b00000000000000000001100001 :
1=
b00000000000000000001100001 ?
b00000000000000000001100010 A
#2960000000
0!
0*
05
0=
#2970000000
1!
1*
15
b00000000000000000001100010 :
1=
b00000000000000000001100010 ?
b00000000000000000001100011 A
#2980000000
0!
0*
05
0=
#2990000000
1!
1*
15
b00000000000000000001100011 :
1=
b00000000000000000001100011 ?
b00000000000000000001100100 A
#3000000000
0!
0*
05
0=
#3010000000
1!
1*
15
b00000000000000000001100100 :
1=
b00000000000000000001100100 ?
b00000000000000000001100101 A
#3020000000
0!
0*
05
0=
#3030000000
1!
1*
15
b00000000000000000001100101 :
1=
b00000000000000000001100101 ?
b00000000000000000001100110 A
#3040000000
0!
0*
05
0=
#3050000000
1!
1*
15
b00000000000000000001100110 :
1=
b00000000000000000001100110 ?
b00000000000000000001100111 A
#3060000000
0!
0*
05
0=
#3070000000
1!
1*
15
b00000000000000000001100111 :
1=
b00000000000000000001100111 ?
b00000000000000000001101000 A
#3080000000
0!
0*
05
0=
#3090000000
1!
1*
15
b00000000000000000001101000 :
1=
b00000000000000000001101000 ?
b00000000000000000001101001 A
#3100000000
0!
0*
05
0=
#3110000000
1!
1*
15
b00000000000000000001101001 :
1=
b00000000000000000001101001 ?
b00000000000000000001101010 A
#3120000000
0!
0*
05
0=
#3130000000
1!
1*
15
b00000000000000000001101010 :
1=
b00000000000000000001101010 ?
b00000000000000000001101011 A
#3140000000
0!
0*
05
0=
#3150000000
1!
1*
15
b00000000000000000001101011 :
1=
b00000000000000000001101011 ?
b00000000000000000001101100 A
#3160000000
0!
0*
05
0=
#3170000000
1!
1*
15
b00000000000000000001101100 :
1=
b00000000000000000001101100 ?
b00000000000000000001101101 A
#3180000000
0!
0*
05
0=
#3190000000
1!
1*
15
b00000000000000000001101101 :
1=
b00000000000000000001101101 ?
b00000000000000000001101110 A
#3200000000
0!
0*
05
0=
#3210000000
1!
1*
15
b00000000000000000001101110 :
1=
b00000000000000000001101110 ?
b00000000000000000001101111 A
#3220000000
0!
0*
05
0=
#3230000000
1!
1*
15
b00000000000000000001101111 :
1=
b00000000000000000001101111 ?
b00000000000000000001110000 A
#3240000000
0!
0*
05
0=
#3250000000
1!
1*
15
b00000000000000000001110000 :
1=
b00000000000000000001110000 ?
b00000000000000000001110001 A
#3260000000
0!
0*
05
0=
#3270000000
1!
1*
15
b00000000000000000001110001 :
1=
b00000000000000000001110001 ?
b00000000000000000001110010 A
#3280000000
0!
0*
05
0=
#3290000000
1!
1*
15
b00000000000000000001110010 :
1=
b00000000000000000001110010 ?
b00000000000000000001110011 A
#3300000000
0!
0*
05
0=
#3310000000
1!
1*
15
b00000000000000000001110011 :
1=
b00000000000000000001110011 ?
b00000000000000000001110100 A
#3320000000
0!
0*
05
0=
#3330000000
1!
1*
15
b00000000000000000001110100 :
1=
b00000000000000000001110100 ?
b00000000000000000001110101 A
#3340000000
0!
0*
05
0=
#3350000000
1!
1*
15
b00000000000000000001110101 :
1=
b00000000000000000001110101 ?
b00000000000000000001110110 A
#3360000000
0!
0*
05
0=
#3370000000
1!
1*
15
b00000000000000000001110110 :
1=
b00000000000000000001110110 ?
b00000000000000000001110111 A
#3380000000
0!
0*
05
0=
#3390000000
1!
1*
15
b00000000000000000001110111 :
1=
b00000000000000000001110111 ?
b00000000000000000001111000 A
#3400000000
0!
0*
05
0=
#3410000000
1!
1*
15
b00000000000000000001111000 :
1=
b00000000000000000001111000 ?
b00000000000000000001111001 A
#3420000000
0!
0*
05
0=
#3430000000
1!
1*
15
b00000000000000000001111001 :
1=
b00000000000000000001111001 ?
b00000000000000000001111010 A
#3440000000
0!
0*
05
0=
#3450000000
1!
1*
15
b00000000000000000001111010 :
1=
b00000000000000000001111010 ?
b00000000000000000001111011 A
#3460000000
0!
0*
05
0=
#3470000000
1!
1*
15
b00000000000000000001111011 :
1=
b00000000000000000001111011 ?
b00000000000000000001111100 A
#3480000000
0!
0*
05
0=
#3490000000
1!
1*
15
b00000000000000000001111100 :
1=
b00000000000000000001111100 ?
b00000000000000000001111101 A
#3500000000
0!
0*
05
0=
#3510000000
1!
1*
15
b00000000000000000001111101 :
1=
b00000000000000000001111101 ?
b00000000000000000001111110 A
#3520000000
0!
0*
05
0=
#3530000000
1!
1*
15
b00000000000000000001111110 :
1=
b00000000000000000001111110 ?
b00000000000000000001111111 A
#3540000000
0!
0*
05
0=
#3550000000
1!
1*
15
b00000000000000000001111111 :
1=
b00000000000000000001111111 ?
b00000000000000000010000000 A
#3560000000
0!
0*
05
0=
#3570000000
1!
1*
15
b00000000000000000010000000 :
1=
b00000000000000000010000000 ?
b00000000000000000010000001 A
#3580000000
0!
0*
05
0=
